Workbook

Sheet Leia-me
A1: Gamifica — Estudo de Precificação para Escolas
A2: Planilha de análise para decidir como cobrar. Todos os valores em R$ são sugestões de mercado, para validar.
B5: COMO USAR
B6: Azul | C6: Célula de ENTRADA — pode alterar à vontade (nº de alunos, preços, etc.).
B7: Amarelo | C7: Premissa-chave / valor de mercado a validar com seu sócio.
B8: Preto | C8: Fórmula — calculada automaticamente; não precisa editar.
B10: ABAS
B11: Benchmark | C11: O que as principais plataformas cobram hoje (com fontes).
B12: Balões de Cobrança | C12: TODOS os itens que se pode cobrar de uma escola (único e recorrente).
B13: Modelo A — Por Aluno | C13: Calculadora do preço por aluno, com faixas por volume.
B14: Modelo B — Pacote | C14: Calculadora do pacote fechado por faixa de tamanho da escola.
B15: Por Aluno x Pacote | C15: Comparação lado a lado + ponto de equilíbrio (break-even).
B16: Público x Privado | C16: Como a cobrança muda entre escola privada e rede pública.
B17: Projeção 3 anos | C17: Simulação de receita (implantação + recorrência) e margem.
B19: RESUMO DA RECOMENDAÇÃO
B20: Modelo híbrido | C20: Pacote fechado por faixa para escolas pequenas/médias (venda simples) + preço por aluno para redes grandes e público (escala).
B21: Sempre cobrar 2 balões no mínimo | C21: 1) Implantação (único) + 2) Licença recorrente (mensal/anual). Os demais balões são add-ons opcionais.
B22: Ancoragem | C22: Cobrar por VALOR (engajamento, jogos exclusivos, sem punição), não por custo. A margem é alta: app leve, instância por escola.

Sheet Benchmark
A1: Benchmark — o que o mercado cobra | F1: Câmbio US$→R$ | G1: 5.4
A2: Concorrentes internacionais têm preço público (por professor). Nacionais são 'sob consulta'. Câmbio editável abaixo.
A4: Plataforma | B4: Modelo | C4: Preço (moeda de origem) | D4: ≈ em R$ | E4: Observação
A5: Kahoot! | B5: Por professor/mês | C5: US$ 10 a 49 (escola: a partir de US$ 29/prof/mês) | D5: =29*$G$1 | E5: Cobra por professor, não por aluno.
A6: Gimkit | B6: Por escola/ano | C6: US$ 1.000/ano (departamento US$ 650/ano) | D6: =1000*$G$1 | E6: Licença de escola anual.
A7: Quizizz (Wayground) | B7: Individual / escola | C7: Indiv. ~US$ 144/ano · escola sob consulta | D7: =144*$G$1 | E7: Time até 30 ~US$ 50/mês.
A8: ClassDojo | B8: Freemium | C8: Núcleo grátis · família US$ 110/ano | D8: =110*$G$1 | E8: Monetiza a família, não a escola.
A9: Classcraft | B9: Enterprise | C9: Sob consulta (grupo HMH) | D9: — | E9: Venda corporativa/rede.
A10: Educacross (BR) | B10: Por aluno | C10: Sob consulta | D10: — | E10: Adaptativa+gamificada, pública e privada.
A11: Gamefic (BR) | B11: Por escola | C11: Sob consulta | D11: — | E11: Rede social gamificada da escola.
A13: Leitura | B13: A maioria cobra POR PROFESSOR. Para uma plataforma que o ALUNO usa todo dia, cobrar por aluno ou por pacote de escola captura muito mais valor.
A15: Fontes: | B15: Kahoot/Gimkit/ClassDojo/Quizizz: páginas de pricing e reviews 2025-2026 (makerstations, easternherald, capterra, saasworthy).
B16: Educacross e Gamefic: sites oficiais (sob consulta).

Sheet Balões de Cobrança
A1: Balões de cobrança — todos os itens possíveis
A2: Menu completo do que se pode cobrar de uma escola. Combine conforme o cliente. Valores sugeridos para validar (amarelo).
A4: # | B4: Balão / item | C4: Tipo | D4: Faixa sugerida (R$) | E4: Quando aplicar
A5: 1 | B5: Implantação / Setup | C5: Único | D5: 1.500 a 4.000 | E5: Configurar a instância, importar alunos/turmas, aplicar marca. Principal receita inicial.
A6: 2 | B6: Taxa de adesão (alternativa leve) | C6: Único | D6: 500 a 1.500 | E6: Quando a escola resiste a setup alto; entrada menor para destravar a venda.
A7: 3 | B7: Licença POR ALUNO | C7: Recorrente | D7: 4 a 9 /aluno/mês | E7: Modelo A. Escala com o tamanho da escola; ideal para redes e público.
A8: 4 | B8: Licença PACOTE FECHADO | C8: Recorrente | D8: 690 / 1.490 / 2.490 /mês | E8: Modelo B. Faixas por tamanho; venda simples para privadas pequenas/médias.
A9: 5 | B9: Treinamento inicial (onboarding) | C9: Único | D9: 800 a 2.500 | E9: Formação dos professores no 1º mês. Pode ser incluído para fechar contrato anual.
A10: 6 | B10: Formação continuada / certificação | C10: Recorrente | D10: 1.200 a 3.600 /ano | E10: Trilha de capacitação e certificado para os professores ao longo do ano.
A11: 7 | B11: Suporte premium / SLA | C11: Recorrente | D11: 300 a 800 /mês | E11: Atendimento prioritário, gerente de conta, SLA de resposta. Básico já incluso.
A12: 8 | B12: Módulos premium / novos jogos | C12: Recorrente | D12: +10% a 25% da licença | E12: Jogos avançados (Sala de Enigmas, Laboratório), relatórios avançados, ao vivo.
A13: 9 | B13: Banco de conteúdo BNCC | C13: Único/Recorr. | D13: 500 a 2.000 | E13: Atividades prontas por ano e disciplina; atualização anual do banco.
A14: 10 | B14: White-label / marca própria | C14: Único + Recorr. | D14: 3.000 setup + 300 /mês | E14: Domínio e identidade da escola/rede. Diferencial para grupos e franquias.
A15: 11 | B15: Integrações (Classroom, ERP, SSO) | C15: Único | D15: 800 a 3.000 /integração | E15: Conectar ao Google Classroom ou ao sistema de gestão da escola.
A16: 12 | B16: Instância dedicada / uptime | C16: Recorrente | D16: incluído ou +200 /mês | E16: Isolamento de dados por escola (já é diferencial nosso) e garantia de disponibilidade.
... A20: 16 | B20: Relatórios institucionais / selo | C20: Add-on | D20: 300 a 1.000 | E20: Relatórios de engajamento para a escola usar em marketing e prestação de contas.
B22: Recomendação: no mínimo Implantação (único) + uma Licença recorrente. O resto é add-on para subir o ticket.

Sheet Modelo A — Por Aluno
A1: Modelo A — Preço por aluno (com faixas por volume)
A2: Quanto mais alunos, menor o preço unitário. Edite os preços (amarelo) e o nº de alunos (azul).
A4: Faixa (min alunos) | B4: até | C4: Preço R$/aluno/mês
A5: 1 | B5: 150 | C5: 8
A6: 151 | B6: 400 | C6: 6.5
A7: 401 | B7: 800 | C7: 5
A8: 801 | B8: 9999+ | C8: 4
A10: CALCULADORA
A11: Nº de alunos da escola | B11: 300
A12: Preço aplicado (R$/aluno/mês) | B12: =INDEX(C5:C8,MATCH(B11,A5:A8,1))
A13: Receita mensal | B13: =B11*B12
A14: Receita anual (x12) | B14: =B13*12

Sheet Modelo B — Pacote
A1: Modelo B — Pacote fechado por faixa de tamanho
A2: Preço fixo mensal por faixa de alunos. Simples de vender. Edite planos e preços (amarelo).
A4: Plano | B4: A partir de (alunos) | C4: Preço R$/mês | D4: Alunos de referência
A5: Essencial | B5: 1 | C5: 690 | D5: até 150
A6: Crescer | B6: 151 | C6: 1490 | D6: 151 a 400
A7: Escola+ | B7: 401 | C7: 2490 | D7: 401 a 800
A8: Rede | B8: 801 | C8: 3990 | D8: 801+ (ou por aluno)
A10: CALCULADORA
A11: Nº de alunos da escola | B11: 300
A12: Plano aplicado | B12: =INDEX(A5:A8,MATCH(B11,B5:B8,1))
A13: Preço mensal | B13: =INDEX(C5:C8,MATCH(B11,B5:B8,1))
A14: Preço anual (x12) | B14: =B13*12

Sheet Por Aluno x Pacote
A1: Por aluno x Pacote — comparação e ponto de equilíbrio
A2: Para cada tamanho de escola: quanto sai em cada modelo e qual rende mais. Puxa preços dos Modelos A e B.
A4: Alunos | B4: Preço/aluno | C4: Por aluno (R$/mês) | D4: Pacote (R$/mês) | E4: Diferença | F4: Rende mais p/ nós
A5: 50 | B5: =INDEX('Modelo A — Por Aluno'!$C$5:$C$8,MATCH(A5,'Modelo A — Por Aluno'!$A$5:$A$8,1)) | C5: =A5*B5 | D5: =INDEX('Modelo B — Pacote'!$C$5:$C$8,MATCH(A5,'Modelo B — Pacote'!$B$5:$B$8,1)) | E5: =C5-D5 | F5: =IF(C5>D5,"Por aluno","Pacote")
A6: 100 | B6: =INDEX('Modelo A — Por Aluno'!$C$5:$C$8,MATCH(A6,'Modelo A — Por Aluno'!$A$5:$A$8,1)) | C6: =A6*B6 | D6: =INDEX('Modelo B — Pacote'!$C$5:$C$8,MATCH(A6,'Modelo B — Pacote'!$B$5:$B$8,1)) | E6: =C6-D6 | F6: =IF(C6>D6,"Por aluno","Pacote")
A7: 150 | B7: =INDEX('Modelo A — Por Aluno'!$C$5:$C$8,MATCH(A7,'Modelo A — Por Aluno'!$A$5:$A$8,1)) | C7: =A7*B7 | D7: =INDEX('Modelo B — Pacote'!$C$5:$C$8,MATCH(A7,'Modelo B — Pacote'!$B$5:$B$8,1)) | E7: =C7-D7 | F7: =IF(C7>D7,"Por aluno","Pacote")
A8: 200 | B8: =INDEX('Modelo A — Por Aluno'!$C$5:$C$8,MATCH(A8,'Modelo A — Por Aluno'!$A$5:$A$8,1)) | C8: =A8*B8 | D8: =INDEX('Modelo B — Pacote'!$C$5:$C$8,MATCH(A8,'Modelo B — Pacote'!$B$5:$B$8,1)) | E8: =C8-D8 | F8: =IF(C8>D8,"Por aluno","Pacote")
A9: 300 | B9: =INDEX('Modelo A — Por Aluno'!$C$5:$C$8,MATCH(A9,'Modelo A — Por Aluno'!$A$5:$A$8,1)) | C9: =A9*B9 | D9: =INDEX('Modelo B — Pacote'!$C$5:$C$8,MATCH(A9,'Modelo B — Pacote'!$B$5:$B$8,1)) | E9: =C9-D9 | F9: =IF(C9>D9,"Por aluno","Pacote")
A10: 400 | B10: =INDEX('Modelo A — Por Aluno'!$C$5:$C$8,MATCH(A10,'Modelo A — Por Aluno'!$A$5:$A$8,1)) | C10: =A10*B10 | D10: =INDEX('Modelo B — Pacote'!$C$5:$C$8,MATCH(A10,'Modelo B — Pacote'!$B$5:$B$8,1)) | E10: =C10-D10 | F10: =IF(C10>D10,"Por aluno","Pacote")
A11: 500 | B11: =INDEX('Modelo A — Por Aluno'!$C$5:$C$8,MATCH(A11,'Modelo A — Por Aluno'!$A$5:$A$8,1)) | C11: =A11*B11 | D11: =INDEX('Modelo B — Pacote'!$C$5:$C$8,MATCH(A11,'Modelo B — Pacote'!$B$5:$B$8,1)) | E11: =C11-D11 | F11: =IF(C11>D11,"Por aluno","Pacote")
A12: 600 | B12: =INDEX('Modelo A — Por Aluno'!$C$5:$C$8,MATCH(A12,'Modelo A — Por Aluno'!$A$5:$A$8,1)) | C12: =A12*B12 | D12: =INDEX('Modelo B — Pacote'!$C$5:$C$8,MATCH(A12,'Modelo B — Pacote'!$B$5:$B$8,1)) | E12: =C12-D12 | F12: =IF(C12>D12,"Por aluno","Pacote")
A13: 800 | B13: =INDEX('Modelo A — Por Aluno'!$C$5:$C$8,MATCH(A13,'Modelo A — Por Aluno'!$A$5:$A$8,1)) | C13: =A13*B13 | D13: =INDEX('Modelo B — Pacote'!$C$5:$C$8,MATCH(A13,'Modelo B — Pacote'!$B$5:$B$8,1)) | E13: =C13-D13 | F13: =IF(C13>D13,"Por aluno","Pacote")
A14: 1000 | B14: =INDEX('Modelo A — Por Aluno'!$C$5:$C$8,MATCH(A14,'Modelo A — Por Aluno'!$A$5:$A$8,1)) | C14: =A14*B14 | D14: =INDEX('Modelo B — Pacote'!$C$5:$C$8,MATCH(A14,'Modelo B — Pacote'!$B$5:$B$8,1)) | E14: =C14-D14 | F14: =IF(C14>D14,"Por aluno","Pacote")
A16: Como ler | B16: Onde 'Por aluno' rende mais, ofereça por aluno (escolas grandes). Onde 'Pacote' rende mais, o pacote protege a receita (escolas pequenas). O ideal é listar os DOIS e a equipe comercial escolhe o melhor para cada caso.

Sheet Público x Privado
A1: Público x Privado — como muda a cobrança
A2: A lógica de venda e o modelo mudam entre a escola privada e a rede pública (licitação).
A4: Aspecto | B4: Escola privada | C4: Rede pública / Secretaria
A5: Quem decide | B5: Diretor/mantenedor — venda rápida (semanas). | C5: Secretaria via licitação/pregão — ciclo longo (meses).
A6: Modelo ideal | B6: Pacote fechado por faixa (simples) ou por aluno. | C6: Por aluno em escala (volume alto, preço menor).
A7: Preço sugerido | B7: R$ 4 a 9/aluno/mês OU pacote R$ 690 a 2.490/mês. | C7: R$ 2 a 6/aluno/mês (grande volume, contrato anual).
A8: Implantação | B8: R$ 1.500 a 4.000 (único). | C8: Item do edital: implantação + formação + suporte on-site.
A9: Treinamento | B9: Onboarding incluso ou add-on. | C9: Formação de professores geralmente obrigatória no edital.
A10: Faturamento | B10: Mensal ou anual antecipado. | C10: Empenho/nota conforme cronograma da prefeitura.
A11: Contrato | B11: 12 meses com renovação automática. | C11: 12 meses, prorrogável; sujeito à Lei 14.133/2021.
A12: Risco | B12: Inadimplência baixa, decisão ágil. | C12: Ciclo e pagamento mais lentos, porém volume e previsibilidade altos.
A13: Diferencial que pesa | B13: Sem punição, jogos exclusivos, portal família. | C13: Relatórios de rede, BNCC, e Índice de Clima por escola.

Sheet Projeção 3 anos
A1: Projeção de receita — 3 anos (simplificada)
A2: Edite as premissas (azul/amarelo). Modelo simplificado: recorrência = MRR do fim do ano x12.
A4: Premissa / Resultado | B4: Ano 1 | C4: Ano 2 | D4: Ano 3
A5: Escolas NOVAS no ano | B5: 8 | C5: 15 | D5: 25
A6: Escolas acumuladas | B6: =B5 | C6: =B6+C5 | D6: =C6+D5
A7: Alunos médios por escola | B7: 250 | C7: 250 | D7: 250
A8: Alunos totais | B8: =B6*B7 | C8: =C6*C7 | D8: =D6*D7
A9: Preço médio R$/aluno/mês | B9: 6 | C9: 6 | D9: 6
A10: MRR no fim do ano | B10: =B8*B9 | C10: =C8*C9 | D10: =D8*D9
A11: Receita recorrente no ano (MRRx12) | B11: =B10*12 | C11: =C10*12 | D11: =D10*12
A12: Ticket médio de implantação (único) | B12: 2500 | C12: 2500 | D12: 2500
A13: Receita de implantação no ano | B13: =B5*B12 | C13: =C5*C12 | D13: =D5*D12
A14: RECEITA TOTAL no ano | B14: =B11+B13 | C14: =C11+C13 | D14: =D11+D13
A15: Margem bruta % | B15: 0.75 | C15: 0.75 | D15: 0.75
A16: Lucro bruto no ano | B16: =B14*B15 | C16: =C14*C15 | D16: =D14*D15
A18: Observações
A19: • Modelo simplificado: assume a recorrência do fim do ano aplicada aos 12 meses (otimista). Para conservador, use MRR médio.
A20: • Margem alta porque o app é leve e a instância por escola tem custo marginal baixo; o maior custo é gente (implantação, suporte, conteúdo).
A21: • Preço médio por aluno é o mix de privado (maior) e público (menor). Ajuste conforme sua meta de vendas.
